README.md
setup.py
asyncio_nats_streaming.egg-info/PKG-INFO
asyncio_nats_streaming.egg-info/SOURCES.txt
asyncio_nats_streaming.egg-info/dependency_links.txt
asyncio_nats_streaming.egg-info/requires.txt
asyncio_nats_streaming.egg-info/top_level.txt
asyncio_nats_streaming.egg-info/zip-safe
stan/__init__.py
stan/aio/__init__.py
stan/aio/client.py
stan/aio/errors.py
stan/pb/__init__.py
stan/pb/protocol_pb2.py